{
  "frames": {
    "red_car-0": {
      "frame": {
        "x": 71,
        "y": 445,
        "w": 53,
        "h": 98
      },
      "rotated": false,
      "trimmed": false,
      "spriteSourceSize": {
        "x": 71,
        "y": 445,
        "w": 53,
        "h": 98
      },
      "sourceSize": {
        "w": 538,
        "h": 560
      }
    },
    "v2_0-0": {
      "frame": {
        "x": 125,
        "y": 15,
        "w": 59,
        "h": 98
      },
      "rotated": false,
      "trimmed": false,
      "spriteSourceSize": {
        "x": 125,
        "y": 15,
        "w": 59,
        "h": 98
      },
      "sourceSize": {
        "w": 538,
        "h": 560
      }
    },
    "v2_0-1": {
      "frame": {
        "x": 184,
        "y": 15,
        "w": 59,
        "h": 98
      },
      "rotated": false,
      "trimmed": false,
      "spriteSourceSize": {
        "x": 184,
        "y": 15,
        "w": 59,
        "h": 98
      },
      "sourceSize": {
        "w": 538,
        "h": 560
      }
    },
    "v2_1-0": {
      "frame": {
        "x": 245,
        "y": 17,
        "w": 59,
        "h": 98
      },
      "rotated": false,
      "trimmed": false,
      "spriteSourceSize": {
        "x": 245,
        "y": 17,
        "w": 59,
        "h": 98
      },
      "sourceSize": {
        "w": 538,
        "h": 560
      }
    },
    "v2_1-1": {
      "frame": {
        "x": 304,
        "y": 17,
        "w": 59,
        "h": 98
      },
      "rotated": false,
      "trimmed": false,
      "spriteSourceSize": {
        "x": 304,
        "y": 17,
        "w": 59,
        "h": 98
      },
      "sourceSize": {
        "w": 538,
        "h": 560
      }
    },
    "v2_2-0": {
      "frame": {
        "x": 59,
        "y": 120,
        "w": 62,
        "h": 100
      },
      "rotated": false,
      "trimmed": false,
      "spriteSourceSize": {
        "x": 59,
        "y": 120,
        "w": 62,
        "h": 100
      },
      "sourceSize": {
        "w": 538,
        "h": 560
      }
    },
    "v2_2-1": {
      "frame": {
        "x": 121,
        "y": 120,
        "w": 62,
        "h": 100
      },
      "rotated": false,
      "trimmed": false,
      "spriteSourceSize": {
        "x": 121,
        "y": 120,
        "w": 62,
        "h": 100
      },
      "sourceSize": {
        "w": 538,
        "h": 560
      }
    },
    "v2_2-2": {
      "frame": {
        "x": 183,
        "y": 120,
        "w": 62,
        "h": 100
      },
      "rotated": false,
      "trimmed": false,
      "spriteSourceSize": {
        "x": 183,
        "y": 120,
        "w": 62,
        "h": 100
      },
      "sourceSize": {
        "w": 538,
        "h": 560
      }
    },
    "v3_0-0": {
      "frame": {
        "x": 5,
        "y": 15,
        "w": 56,
        "h": 137
      },
      "rotated": false,
      "trimmed": false,
      "spriteSourceSize": {
        "x": 5,
        "y": 15,
        "w": 56,
        "h": 137
      },
      "sourceSize": {
        "w": 538,
        "h": 560
      }
    },
    "v3_1-0": {
      "frame": {
        "x": 5,
        "y": 191,
        "w": 56,
        "h": 137
      },
      "rotated": false,
      "trimmed": false,
      "spriteSourceSize": {
        "x": 5,
        "y": 191,
        "w": 56,
        "h": 137
      },
      "sourceSize": {
        "w": 538,
        "h": 560
      }
    },
    "v3_2-0": {
      "frame": {
        "x": 424,
        "y": 20,
        "w": 64,
        "h": 139
      },
      "rotated": false,
      "trimmed": false,
      "spriteSourceSize": {
        "x": 424,
        "y": 20,
        "w": 64,
        "h": 139
      },
      "sourceSize": {
        "w": 538,
        "h": 560
      }
    }
  },
  "meta": {
    "app": "sprite-sheet-to-json",
    "version": "1.0.0",
    "image": "bk_cars1.a.png",
    "format": "RGBA8888",
    "size": {
      "w": 538,
      "h": 560
    },
    "scale": "1"
  }
}